{
  "DraftItem": {
    "TradeItem": {
      "IsBrandBankPublication": false,
      "TargetSector": [
        "UDI_REGISTRY"
      ],
      "MedicalDeviceTradeItemModule": {
        "MedicalDeviceInformation": {
          "EUMedicalDeviceStatusCode": {
            "Value": "ON_MARKET"
          }
        }
      },
      "IsTradeItemABaseUnit": false,
      "IsTradeItemADespatchUnit": true,
      "IsTradeItemAnOrderableUnit": true,
      "TradeItemUnitDescriptorCode": {
        "Value": "CASE"
      },
      "TradeItemTradeChannelCode": [
        {
          "Value": "UDI_REGISTRY"
        }
      ],
      "InformationProviderOfTradeItem": {
        "Gln": "7612345000480",
        "PartyName": "EUDAMED Public Download Importing"
      },
      "GdsnTradeItemClassification": {
        "GpcSegmentCode": "51000000",
        "GpcClassCode": "51150100",
        "GpcFamilyCode": "51150000",
        "GpcCategoryCode": "10005844",
        "GpcCategoryName": "Medical Devices"
      },
      "NextLowerLevelTradeItemInformation": {
        "QuantityOfChildren": 1,
        "TotalQuantityOfNextLowerLevelTradeItem": 30,
        "ChildTradeItem": [
          {
            "QuantityOfNextLowerLevelTradeItem": 30,
            "Gtin": "04250203274432"
          }
        ]
      },
      "TargetMarket": {
        "TargetMarketCountryCode": {
          "Value": "097"
        }
      },
      "TradeItemContactInformation": [
        {
          "ContactTypeCode": {
            "Value": "EMA"
          },
          "AdditionalPartyIdentification": [
            {
              "AdditionalPartyIdentificationTypeCode": "SRN",
              "Value": "DE-MF-000004967"
            }
          ],
          "ContactName": "Primed Halberstadt Medizintechnik GmbH"
        }
      ],
      "TradeItemSynchronisationDates": {
        "LastChangeDateTime": "2026-03-26T10:10:22",
        "EffectiveDateTime": "2026-03-26T10:10:22",
        "PublicationDateTime": "2026-03-26T10:10:22"
      },
      "GlobalModelInformation": [
        {
          "GlobalModelNumber": "42502032PRI0264S"
        }
      ],
      "Gtin": "04250203274449"
    },
    "CatalogueItemChildItemLink": [
      {
        "Quantity": 30,
        "CatalogueItem": {
          "Identifier": "51925269-4c55-48b1-82d3-09a78648f52b",
          "TradeItem": {
            "IsBrandBankPublication": false,
            "TargetSector": [
              "UDI_REGISTRY"
            ],
            "MedicalDeviceTradeItemModule": {
              "MedicalDeviceInformation": {
                "EUMedicalDeviceStatusCode": {
                  "Value": "ON_MARKET"
                }
              }
            },
            "IsTradeItemABaseUnit": false,
            "IsTradeItemADespatchUnit": false,
            "IsTradeItemAnOrderableUnit": true,
            "TradeItemUnitDescriptorCode": {
              "Value": "PACK_OR_INNER_PACK"
            },
            "TradeItemTradeChannelCode": [
              {
                "Value": "UDI_REGISTRY"
              }
            ],
            "InformationProviderOfTradeItem": {
              "Gln": "7612345000480",
              "PartyName": "EUDAMED Public Download Importing"
            },
            "GdsnTradeItemClassification": {
              "GpcSegmentCode": "51000000",
              "GpcClassCode": "51150100",
              "GpcFamilyCode": "51150000",
              "GpcCategoryCode": "10005844",
              "GpcCategoryName": "Medical Devices"
            },
            "NextLowerLevelTradeItemInformation": {
              "QuantityOfChildren": 1,
              "TotalQuantityOfNextLowerLevelTradeItem": 10,
              "ChildTradeItem": [
                {
                  "QuantityOfNextLowerLevelTradeItem": 10,
                  "Gtin": "04250203274456"
                }
              ]
            },
            "TargetMarket": {
              "TargetMarketCountryCode": {
                "Value": "097"
              }
            },
            "TradeItemContactInformation": [
              {
                "ContactTypeCode": {
                  "Value": "EMA"
                },
                "AdditionalPartyIdentification": [
                  {
                    "AdditionalPartyIdentificationTypeCode": "SRN",
                    "Value": "DE-MF-000004967"
                  }
                ],
                "ContactName": "Primed Halberstadt Medizintechnik GmbH"
              }
            ],
            "TradeItemSynchronisationDates": {
              "LastChangeDateTime": "2026-03-26T10:10:22",
              "EffectiveDateTime": "2026-03-26T10:10:22",
              "PublicationDateTime": "2026-03-26T10:10:22"
            },
            "GlobalModelInformation": [
              {
                "GlobalModelNumber": "42502032PRI0264S"
              }
            ],
            "Gtin": "04250203274432"
          },
          "CatalogueItemChildItemLink": [
            {
              "Quantity": 10,
              "CatalogueItem": {
                "Identifier": "8607de2a-5cbb-423d-8b26-cc76dddcbb85",
                "TradeItem": {
                  "IsBrandBankPublication": false,
                  "TargetSector": [
                    "UDI_REGISTRY"
                  ],
                  "HealthcareItemInformationModule": {
                    "HealthcareItemInformation": {
                      "DoesTradeItemContainHumanBloodDerivative": "FALSE",
                      "DoesTradeItemContainLatex": "FALSE",
                      "DoesTradeItemContainHumanTissue": "FALSE",
                      "DoesTradeItemContainAnimalTissue": false
                    }
                  },
                  "MedicalDeviceTradeItemModule": {
                    "MedicalDeviceInformation": {
                      "IsTradeItemImplantable": "FALSE",
                      "UdidDeviceCount": 1,
                      "HasDeviceMeasuringFunction": false,
                      "IsActiveDevice": false,
                      "IsDeviceIntendedToAdministerOrRemoveMedicinalProduct": false,
                      "IsDeviceMedicinalProduct": false,
                      "IsReprocessedSingleUseDevice": false,
                      "IsReusableSurgicalInstrument": false,
                      "UDIProductionIdentifierTypeCode": [
                        {
                          "Value": "BATCH_NUMBER"
                        },
                        {
                          "Value": "MANUFACTURING_DATE"
                        },
                        {
                          "Value": "EXPIRATION_DATE"
                        }
                      ],
                      "MultiComponentDeviceTypeCode": {
                        "Value": "DEVICE"
                      },
                      "EUMedicalDeviceStatusCode": {
                        "Value": "ON_MARKET"
                      },
                      "HealthcareTradeItemReusabilityInformation": {
                        "ManufacturerDeclaredReusabilityTypeCode": {
                          "Value": "SINGLE_USE"
                        }
                      },
                      "TradeItemSterilityInformation": {
                        "InitialManufacturerSterilisationCode": [
                          {
                            "Value": "NOT_STERILISED"
                          }
                        ],
                        "InitialSterilisationPriorToUseCode": [
                          {
                            "Value": "NO_STERILISATION_REQUIRED"
                          }
                        ]
                      }
                    }
                  },
                  "RegulatedTradeItemModule": {
                    "RegulatoryInformation": [
                      {
                        "RegulatoryAct": "MDR",
                        "RegulatoryAgency": "EU"
                      }
                    ]
                  },
                  "SalesInformationModule": {
                    "SalesInformation": {
                      "TargetMarketSalesConditions": [
                        {
                          "TargetMarketConsumerSalesConditionCode": {
                            "Value": "ORIGINAL_PLACED"
                          },
                          "SalesConditionTargetMarketCountry": [
                            {
                              "CountryCode": {
                                "Value": "276"
                              }
                            }
                          ]
                        }
                      ]
                    }
                  },
                  "TradeItemDescriptionModule": {
                    "TradeItemDescriptionInformation": {
                      "TradeItemDescription": [
                        {
                          "LanguageCode": "de",
                          "Value": "NovaPhon Sprechventil, signal orange mit O2-Anschluss, 10 Stück/Faltschachtel"
                        }
                      ]
                    }
                  },
                  "IsTradeItemABaseUnit": true,
                  "IsTradeItemADespatchUnit": false,
                  "IsTradeItemAnOrderableUnit": true,
                  "TradeItemUnitDescriptorCode": {
                    "Value": "BASE_UNIT_OR_EACH"
                  },
                  "TradeItemTradeChannelCode": [
                    {
                      "Value": "UDI_REGISTRY"
                    }
                  ],
                  "InformationProviderOfTradeItem": {
                    "Gln": "7612345000480",
                    "PartyName": "EUDAMED Public Download Importing"
                  },
                  "GdsnTradeItemClassification": {
                    "GpcSegmentCode": "51000000",
                    "GpcClassCode": "51150100",
                    "GpcFamilyCode": "51150000",
                    "GpcCategoryCode": "10005844",
                    "GpcCategoryName": "Medical Devices",
                    "AdditionalTradeItemClassification": [
                      {
                        "AdditionalTradeItemClassificationSystemCode": {
                          "Value": "76"
                        },
                        "AdditionalTradeItemClassificationValue": [
                          {
                            "AdditionalTradeItemClassificationCodeValue": "EU_CLASS_IIA"
                          }
                        ]
                      },
                      {
                        "AdditionalTradeItemClassificationSystemCode": {
                          "Value": "88"
                        },
                        "AdditionalTradeItemClassificationValue": [
                          {
                            "AdditionalTradeItemClassificationCodeValue": "R90060202"
                          }
                        ]
                      }
                    ]
                  },
                  "TargetMarket": {
                    "TargetMarketCountryCode": {
                      "Value": "097"
                    }
                  },
                  "TradeItemContactInformation": [
                    {
                      "ContactTypeCode": {
                        "Value": "EMA"
                      },
                      "AdditionalPartyIdentification": [
                        {
                          "AdditionalPartyIdentificationTypeCode": "SRN",
                          "Value": "DE-MF-000004967"
                        }
                      ],
                      "ContactName": "Primed Halberstadt Medizintechnik GmbH"
                    }
                  ],
                  "TradeItemSynchronisationDates": {
                    "LastChangeDateTime": "2026-03-26T10:10:22",
                    "EffectiveDateTime": "2026-02-13T07:54:02.489",
                    "PublicationDateTime": "2026-03-26T10:10:22"
                  },
                  "GlobalModelInformation": [
                    {
                      "GlobalModelNumber": "42502032PRI0264S",
                      "GlobalModelDescription": [
                        {
                          "LanguageCode": "en",
                          "Value": "04250203274456"
                        }
                      ]
                    }
                  ],
                  "Gtin": "04250203274456",
                  "AdditionalTradeItemIdentification": [
                    {
                      "AdditionalTradeItemIdentificationTypeCode": "MANUFACTURER_PART_NUMBER",
                      "Value": "200243-10"
                    },
                    {
                      "AdditionalTradeItemIdentificationTypeCode": "MODEL_NUMBER",
                      "Value": "Sprechventile mit O2-Anschluss"
                    }
                  ]
                }
              }
            }
          ]
        }
      }
    ],
    "Identifier": "Draft_13df0639-c215-4e32-bb6a-9fddd4a07e84"
  }
}